singer/__init__.py
singer/bookmarks.py
singer/catalog.py
singer/logger.py
singer/logging.conf
singer/messages.py
singer/metadata.py
singer/metrics.py
singer/requests.py
singer/schema.py
singer/statediff.py
singer/transform.py
singer/utils.py
pipelinewise_singer_python-2.0.1.dist-info/LICENSE
pipelinewise_singer_python-2.0.1.dist-info/METADATA
pipelinewise_singer_python-2.0.1.dist-info/WHEEL
pipelinewise_singer_python-2.0.1.dist-info/top_level.txt
pipelinewise_singer_python-2.0.1.dist-info/RECORD
