Metadata-Version: 2.1
Name: pipelinewise-singer-python
Version: 2.0.1
Summary: Singer.io utility library - PipelineWise compatible
Home-page: https://github.com/transferwise/pipelinewise-singer-python
Author: TransferWise
License: UNKNOWN
Platform: UNKNOWN
Classifier: License :: OSI Approved :: Apache Software License
Classifier: Programming Language :: Python :: 3 :: Only
License-File: LICENSE
Requires-Dist: pytz
Requires-Dist: jsonschema (==3.2.0)
Requires-Dist: orjson (==3.6.1)
Requires-Dist: python-dateutil (>=2.6.0)
Requires-Dist: backoff (==1.11.1)
Requires-Dist: ciso8601
Provides-Extra: dev
Requires-Dist: pylint (==2.11.1) ; extra == 'dev'
Requires-Dist: ipython ; extra == 'dev'
Requires-Dist: ipdb ; extra == 'dev'
Requires-Dist: nose ; extra == 'dev'
Requires-Dist: unify (==0.5) ; extra == 'dev'
